ideas/__init__.py
ideas/__main__.py
ideas/console.py
ideas/custom_encoding.py
ideas/experimental_syntax_encoding.py
ideas/import_hook.py
ideas/lambda_encoding.py
ideas/main_hack.py
ideas/patching_hook.py
ideas/session.py
ideas/utils.py
ideas/examples/__init__.py
ideas/examples/auto_self.py
ideas/examples/confused_math_bc.py
ideas/examples/constants.py
ideas/examples/decimal_math.py
ideas/examples/decimal_math_d.py
ideas/examples/decimal_math_with.py
ideas/examples/easy_units.py
ideas/examples/experimental_syntax.py
ideas/examples/fractions_ast.py
ideas/examples/fractions_tok.py
ideas/examples/french.py
ideas/examples/french_repeat.py
ideas/examples/function_keyword.py
ideas/examples/function_simplest.py
ideas/examples/implicit_multiplication.py
ideas/examples/lambda_codec.py
ideas/examples/nfc_normalization.py
ideas/examples/nicer_floats.py
ideas/examples/nobreak.py
ideas/examples/pythonji.py
ideas/examples/rational_math.py
ideas/examples/repeat.py
ideas/examples/switch.py
ideas/examples/unnormalized_unicode.py
tests/auto_self/__init__.py
tests/auto_self/test_auto_self.py
tests/confused_math_bc/__init__.py
tests/confused_math_bc/confused_math.py
tests/confused_math_bc/test_confused_math_bc.py
tests/constants/__init__.py
tests/constants/final.py
tests/constants/test_constants.py
tests/constants/uppercase.py
tests/constants/usercustomize.py
tests/decimal_math/__init__.py
tests/decimal_math/test_decimal_math.py
tests/decimal_math/use_encoding.py
tests/decimal_math/use_hook.py
tests/fractions_ast/__init__.py
tests/fractions_ast/addition.py
tests/fractions_ast/test_fractions_ast.py
tests/fractions_tok/__init__.py
tests/fractions_tok/addition.py
tests/fractions_tok/test_fractions_tok.py
tests/french/__init__.py
tests/french/mon_programme.py
tests/french/test_french.py
tests/function_keyword/__init__.py
tests/function_keyword/my_program.py
tests/function_keyword/test_function.py
tests/implicit_multiplication/__init__.py
ideas-0.1.5.dist-info/LICENSE
ideas-0.1.5.dist-info/METADATA
ideas-0.1.5.dist-info/WHEEL
ideas-0.1.5.dist-info/entry_points.txt
ideas-0.1.5.dist-info/top_level.txt
ideas-0.1.5.dist-info/RECORD
