Metadata-Version: 2.1
Name: ideas
Version: 0.1.5
Summary: Easy creation of import hooks to test ideas.
Home-page: https://github.com/aroberge/ideas
Author: André Roberge
Author-email: Andre.Roberge@gmail.com
Classifier: Development Status :: 1 - Planning
Classifier: License :: OSI Approved :: MIT License
Classifier: Programming Language :: Python :: 3
Classifier: Programming Language :: Python :: 3.6
Classifier: Programming Language :: Python :: 3.7
Classifier: Programming Language :: Python :: 3.8
Classifier: Programming Language :: Python :: 3.9
Classifier: Programming Language :: Python :: 3.10
Requires-Python: >=3.6
License-File: LICENSE
Requires-Dist: token-utils
